lol.py
lol_lmao_even-1.0.0.dist-info/licenses/LICENSE.txt
lol_lmao_even-1.0.0.dist-info/METADATA
lol_lmao_even-1.0.0.dist-info/WHEEL
lol_lmao_even-1.0.0.dist-info/entry_points.txt
lol_lmao_even-1.0.0.dist-info/top_level.txt
lol_lmao_even-1.0.0.dist-info/RECORD
