Metadata-Version: 2.4
Name: lol-lmao-even
Version: 1.0.0
Summary: lol, lmao even
Author: Slackow
License: MIT License
Project-URL: Repository, https://github.com/Slackow/lol-lmao-even.git
Project-URL: Issues, https://github.com/Slackow/lol-lmao-even/issues
Project-URL: Download, https://github.com/Slackow/lol-lmao-even/releases
Project-URL: Changelog, https://github.com/Slackow/lol-lmao-even/releases
Keywords: lol,lmao,even
Requires-Python: >=3.0
License-File: LICENSE.txt
Dynamic: license-file
